aiearth/predict/__init__.py
aiearth/predict/adapter/__init__.py
aiearth/predict/adapter/toolbox/__init__.py
aiearth/predict/adapter/toolbox/input_args.py
aiearth/predict/adapter/toolbox/parser.py
aiearth/predict/checkpoint/__init__.py
aiearth/predict/checkpoint/downloader.py
aiearth/predict/checkpoint/model_checkpoint.py
aiearth/predict/checkpoint/model_config.py
aiearth/predict/config/__init__.py
aiearth/predict/config/constants.py
aiearth/predict/config/log_level.py
aiearth/predict/config/runtime_environment.py
aiearth/predict/dataset/__init__.py
aiearth/predict/dataset/read_api.py
aiearth/predict/dataset/datasource/__init__.py
aiearth/predict/dataset/datasource/raster_dataset_reader.py
aiearth/predict/dataset/datasource/raster_datasource.py
aiearth/predict/dataset/raster/__init__.py
aiearth/predict/dataset/raster/aie_geoserver_raster_dataset.py
aiearth/predict/dataset/raster/raster_dataset.py
aiearth/predict/dataset/raster/rasterio_dataset.py
aiearth/predict/dataset/raster/tiff_file_raster_dataset.py
aiearth/predict/dataset/vector/__init__.py
aiearth/predict/dataset/vector/shape_file_vector_dataset.py
aiearth/predict/dataset/vector/vector_dataset.py
aiearth/predict/deploy/__init__.py
aiearth/predict/deploy/client/__init__.py
aiearth/predict/deploy/client/model_project_client.py
aiearth/predict/deploy/client/model_version_client.py
aiearth/predict/deploy/client/remote_client.py
aiearth/predict/deploy/client/sdk_client.py
aiearth/predict/deploy/client/toolbox_client.py
aiearth/predict/deploy/client/toolbox_deploy_status.py
aiearth/predict/deploy/schema/__init__.py
aiearth/predict/deploy/schema/job_config.py
aiearth/predict/deploy/schema/runtime_env.py
aiearth/predict/deploy/schema/toolbox_run_config.py
aiearth/predict/deploy/sdk/__init__.py
aiearth/predict/deploy/sdk/project.py
aiearth/predict/deploy/sdk/toolbox.py
aiearth/predict/deploy/sdk/version.py
aiearth/predict/error/__init__.py
aiearth/predict/error/biz_error.py
aiearth/predict/error/error_code.py
aiearth_predict-0.0.2.dist-info/LICENSE
aiearth_predict-0.0.2.dist-info/METADATA
aiearth_predict-0.0.2.dist-info/WHEEL
aiearth_predict-0.0.2.dist-info/top_level.txt
aiearth_predict-0.0.2.dist-info/RECORD
